redzoo/__init__.py
redzoo/backup/__init__.py
redzoo/backup/backup.py
redzoo/database/__init__.py
redzoo/database/simple.py
redzoo/math/__init__.py
redzoo/math/display.py
redzoo/metrics/__init__.py
redzoo/metrics/consumption.py
redzoo-1.0.0.dist-info/licenses/LICENSE
redzoo-1.0.0.dist-info/METADATA
redzoo-1.0.0.dist-info/WHEEL
redzoo-1.0.0.dist-info/top_level.txt
redzoo-1.0.0.dist-info/RECORD
