Metadata-Version: 2.4
Name: redzoo
Version: 1.0.0
Summary: utilities
Author: Gregor Roth
Author-email: gregor.roth@web.de
Requires-Python: >=3.8
License-File: LICENSE
Requires-Dist: appdirs==1.4.4
Dynamic: license-file
